lcsspy/__init__.py
lcsspy/lcss.py
lcsspy-1.0.1.dist-info/METADATA
lcsspy-1.0.1.dist-info/WHEEL
lcsspy-1.0.1.dist-info/licenses/LICENSE.txt
lcsspy-1.0.1.dist-info/RECORD
