Metadata-Version: 2.1
Name: lcsspy
Version: 1.0.1
Summary: Longest Common Subsequence (LCSS) computation to measure similarity for time series.
Project-URL: Homepage, https://github.com/francescolafratta/lcsspy
Project-URL: Documentation, https://francescolafratta.github.io/lcsspy/
Project-URL: Issues, https://github.com/francescolafratta/lcsspy/issues
Author-email: Francesco Lafratta <fl.novacta@outlook.com>
Maintainer-email: Francesco Lafratta <fl.novacta@outlook.com>
License: MIT License
License-File: LICENSE.txt
Keywords: lcss,lcsspy,similarity,time series
Classifier: License :: OSI Approved :: MIT License
Classifier: Operating System :: OS Independent
Classifier: Programming Language :: Python :: 3
Requires-Python: >=3.9
Requires-Dist: matplotlib>=3.8.0
Requires-Dist: numpy>=1.26.1
Requires-Dist: pandas>=2.1.2
Provides-Extra: tests
Requires-Dist: pytest>=7.4.3; extra == 'tests'
